README
setup.py
commando/__init__.py
commando/models.py
commando/tests.py
commando/contrib/__init__.py
commando/contrib/cms/__init__.py
commando/contrib/cms/models.py
commando/contrib/cms/management/__init__.py
commando/contrib/cms/management/cms.py
commando/contrib/cms/management/publisher_publish.py
commando/contrib/cms/management/commands/__init__.py
commando/contrib/cms/management/commands/cms.py
commando/contrib/cms/management/commands/publisher_publish.py
commando/contrib/haystack/__init__.py
commando/contrib/haystack/models.py
commando/contrib/haystack/management/__init__.py
commando/contrib/haystack/management/build_solr_schema.py
commando/contrib/haystack/management/clear_index.py
commando/contrib/haystack/management/haystack_info.py
commando/contrib/haystack/management/rebuild_index.py
commando/contrib/haystack/management/update_index.py
commando/contrib/haystack/management/commands/__init__.py
commando/contrib/haystack/management/commands/build_solr_schema.py
commando/contrib/haystack/management/commands/clear_index.py
commando/contrib/haystack/management/commands/haystack_info.py
commando/contrib/haystack/management/commands/rebuild_index.py
commando/contrib/haystack/management/commands/update_index.py
commando/contrib/south/__init__.py
commando/contrib/south/models.py
commando/contrib/south/management/__init__.py
commando/contrib/south/management/convert_to_south.py
commando/contrib/south/management/datamigration.py
commando/contrib/south/management/graphmigrations.py
commando/contrib/south/management/migrate.py
commando/contrib/south/management/migrationcheck.py
commando/contrib/south/management/schemamigration.py
commando/contrib/south/management/startmigration.py
commando/contrib/south/management/commands/__init__.py
commando/contrib/south/management/commands/convert_to_south.py
commando/contrib/south/management/commands/datamigration.py
commando/contrib/south/management/commands/graphmigrations.py
django_commando.egg-info/PKG-INFO
django_commando.egg-info/SOURCES.txt
django_commando.egg-info/dependency_links.txt
django_commando.egg-info/requires.txt
django_commando.egg-info/top_level.txt