Metadata-Version: 1.1
Name: django-commando
Version: 0.1.1
Summary: A declarative API for writing, overriding and sequencing Django management commands
Home-page: https://github.com/skibblenybbles/django-commando
Author: Mike Kibbel
Author-email: mkibbel@gmail.com
License: MIT License
Platform: OS Independent
Classifier: Development Status :: 4 - Beta
Classifier: Environment :: Web Environment
Classifier: Framework :: Django
Classifier: Intended Audience :: Developers
Classifier: License :: OSI Approved :: MIT License
Classifier: Natural Language :: English
Classifier: Operating System :: OS Independent
Classifier: Programming Language :: Python
Classifier: Topic :: Software Development :: Libraries :: Application Frameworks
Classifier: Topic :: Software Development :: Libraries :: Python Modules
Classifier: Topic :: Utilities
